ctfsolver/__init__.py
ctfsolver/find_usage/__init__.py
ctfsolver/find_usage/__main__.py
ctfsolver/folders/__init__.py
ctfsolver/folders/__main__.py
ctfsolver/scripts/__init__.py
ctfsolver/scripts/__main__.py
ctfsolver/scripts/run_folders.py
ctfsolver/scripts/run_solution.py
ctfsolver/src/__init__.py
ctfsolver/src/ctfsolver.py
ctfsolver/template/__init__.py
ctfsolver/template/__main__.py
ctfsolver/template/solution_template.py
ctfsolver/test/__init__.py
ctfsolver-0.0.12.dist-info/licenses/LICENSE
ctfsolver-0.0.12.dist-info/METADATA
ctfsolver-0.0.12.dist-info/WHEEL
ctfsolver-0.0.12.dist-info/entry_points.txt
ctfsolver-0.0.12.dist-info/top_level.txt
ctfsolver-0.0.12.dist-info/RECORD
