Metadata-Version: 2.4
Name: ctfsolver
Version: 0.0.12
Summary: An all in one library for solving CTF challenges
Author: Nikolas Filippatos
License: MIT
Project-URL: Homepage, https://github.com/nikolasfil/CTFSolverScript
Classifier: License :: OSI Approved :: MIT License
Classifier: Programming Language :: Python :: 3.11
Classifier: Operating System :: OS Independent
Requires-Python: >=3.11
License-File: LICENSE
Requires-Dist: build>=0.7.0
Requires-Dist: pwntools>=4.0.0
Requires-Dist: scapy>=2.0.0
Requires-Dist: argcomplete>=2.0.0
Requires-Dist: setuptools>=67.7.0
Requires-Dist: wheel>=0.37.0
Requires-Dist: dash_cytoscape>=1.0.2
Requires-Dist: dash>=3.2.0
Provides-Extra: dev
Requires-Dist: pytest>=6.2.4; extra == "dev"
Requires-Dist: twine>=3.4.2; extra == "dev"
Requires-Dist: pipdeptree>=2.0.0; extra == "dev"
Requires-Dist: pylint>=3.3.7; extra == "dev"
Provides-Extra: docs
Requires-Dist: sphinx>=8.0.0; extra == "docs"
Requires-Dist: myst-parser>=3.0.0; extra == "docs"
Requires-Dist: furo>=2024.0.0; extra == "docs"
Requires-Dist: sphinx-copybutton>=0.5.2; extra == "docs"
Requires-Dist: sphinx-autodoc-typehints>=2.4.4; extra == "docs"
Requires-Dist: sphinx-basic-ng>=1.0.0.beta2; extra == "docs"
Requires-Dist: sphinx-rtd-theme>=3.0.2; extra == "docs"
Requires-Dist: python-call-graph>=2.1.4; extra == "docs"
Provides-Extra: docs-live
Requires-Dist: sphinx-autobuild>=2024.9.3; extra == "docs-live"
Provides-Extra: docs-autoapi
Requires-Dist: sphinx-autoapi>=3.0.0; extra == "docs-autoapi"
Dynamic: license-file
